{
  "projectId": "gen-lang-client-0896148555",
  "appId": "1:977382376587:web:e01f28f0a80d4363d9008e",
  "apiKey": "AIzaSyCkqu3_poJ5p2eSG6fIuZBe5y16tTpGfSs",
  "authDomain": "gen-lang-client-0896148555.firebaseapp.com",
  "firestoreDatabaseId": "ai-studio-remix2bahiagurme-0abfb19f-c6f4-42db-8d8f-7d03e8133279",
  "storageBucket": "gen-lang-client-0896148555.firebasestorage.app",
  "messagingSenderId": "977382376587",
  "measurementId": "",
  "oAuthClientId": "977382376587-dem55v3oq7qa6go61o6rua56660tugof.apps.googleusercontent.com"
}